rcttools/__init__.py
rcttools/alphabet.py
rcttools/common.py
rcttools/data/-.png
rcttools/data/0.png
rcttools/data/1.png
rcttools/data/2.png
rcttools/data/3.png
rcttools/data/4.png
rcttools/data/5.png
rcttools/data/6.png
rcttools/data/7.png
rcttools/data/8.png
rcttools/data/9.png
rcttools/rct2gpx.py
rcttools/tests/__init__.py
rcttools/tests/test_common.py
rcttools/tests/test_format.py
rcttools/tests/test_import.py~
rcttools/text_format.py
rcttools-0.2.0.dist-info/WHEEL
rcttools-0.2.0.dist-info/entry_points.txt
rcttools-0.2.0.dist-info/METADATA
rcttools-0.2.0.dist-info/RECORD
