Metadata-Version: 2.3
Name: rcttools
Version: 0.2.0
Summary: Community tools for archiving and processing footage from the Garmin Varia RCT715 bike camera/radar
Keywords: GPX,Garmin,Varia,Cycling
Author: Christopher Whelan
Author-email: Christopher Whelan <topherwhelan@gmail.com>
Classifier: Development Status :: 3 - Alpha
Classifier: Intended Audience :: Other Audience
Requires-Dist: ffmpeg-python
Requires-Dist: numpy
Requires-Dist: python-dateutil
Requires-Dist: pillow
Requires-Dist: pandas>=1.0
Requires-Dist: types-pillow
Requires-Dist: types-python-dateutil
Requires-Dist: pandas-stubs
Requires-Dist: mypy
Requires-Dist: gpxpy>=1.6.2
Requires-Dist: exif>=1.6.1
Requires-Python: >=3.10
